DiscordAlertsTrader/__init__.py
DiscordAlertsTrader/alerts_tracker.py
DiscordAlertsTrader/alerts_trader.py
DiscordAlertsTrader/calc_strat.py
DiscordAlertsTrader/configurator.py
DiscordAlertsTrader/discord_bot.py
DiscordAlertsTrader/fend_bot.py
DiscordAlertsTrader/gui.py
DiscordAlertsTrader/gui_generator.py
DiscordAlertsTrader/gui_layouts.py
DiscordAlertsTrader/message_parser.py
DiscordAlertsTrader/plot_hist_quotes.py
DiscordAlertsTrader/port_sim.py
DiscordAlertsTrader/server_alert_formatting.py
DiscordAlertsTrader/brokerages/TDA_api.py
DiscordAlertsTrader/brokerages/__init__.py
DiscordAlertsTrader/brokerages/eTrade_api.py
DiscordAlertsTrader/brokerages/weBull_api.py
tests/__init__.py
tests/mock_discord_message.py
tests/test_AlertsTracker.py
tests/test_AlertsTrader.py
tests/test_AlertsTrader_exits.py
tests/test_TDA.py
tests/test_calc_strat.py
tests/test_configurator.py
tests/test_discord_bot.py
tests/test_gui_generator.py
tests/test_msg_parsed.py
DiscordAlertsTrader-1.0.2.dist-info/LICENSE
DiscordAlertsTrader-1.0.2.dist-info/METADATA
DiscordAlertsTrader-1.0.2.dist-info/WHEEL
DiscordAlertsTrader-1.0.2.dist-info/entry_points.txt
DiscordAlertsTrader-1.0.2.dist-info/top_level.txt
DiscordAlertsTrader-1.0.2.dist-info/RECORD
