Metadata-Version: 2.1
Name: DiscordAlertsTrader
Version: 1.0.2
Summary: Package for automating discord trade alerts in TDA or eTrade.
Home-page: 
Download-URL: https://github.com/AdoNunes/DiscordAlertsTrader
Author: Adonay Nunes
Author-email: adonays.nunes@gmail.com
License: BSD (3-clause)
Classifier: License :: OSI Approved :: BSD License
Classifier: Programming Language :: Python :: 3.9
Classifier: Topic :: Communications :: Chat
Classifier: Topic :: Office/Business :: Financial
Classifier: Topic :: Software Development :: Libraries :: Python Modules
Classifier: Intended Audience :: Developers
Classifier: Intended Audience :: Financial and Insurance Industry
Classifier: Intended Audience :: Information Technology
Classifier: Operating System :: Microsoft :: Windows
License-File: LICENSE
Requires-Dist: requests (==2.28.1)
Requires-Dist: td-ameritrade-python-api
Requires-Dist: PySimpleGUIQt
Requires-Dist: pandas
Requires-Dist: numpy
Requires-Dist: colorama
Requires-Dist: discord.py-self
Requires-Dist: pyetrade
Requires-Dist: discord-webhook
Requires-Dist: webull
Requires-Dist: matplotlib
